maskit/__init__.py
maskit/dataset.py
maskit/loss.py
maskit/model.py
maskit/utils.py
maskit_learn-0.1.4.dist-info/licenses/LICENSE
maskit_learn-0.1.4.dist-info/METADATA
maskit_learn-0.1.4.dist-info/WHEEL
maskit_learn-0.1.4.dist-info/top_level.txt
maskit_learn-0.1.4.dist-info/RECORD
