Metadata-Version: 2.4
Name: maskit-learn
Version: 0.1.4
Summary: [MASK]it -Efficient pre-trained encoder adaption leveraging the [MASK]
Author-email: Eugenia Alleva <eugenia.alleva@gmail.com>
License: Apache 2.0
Requires-Python: >=3.10.16
License-File: LICENSE
Requires-Dist: transformers
Requires-Dist: torch
Provides-Extra: dev
Requires-Dist: pytest; extra == "dev"
Requires-Dist: black; extra == "dev"
Requires-Dist: flake8; extra == "dev"
Dynamic: license-file
